reformer_fastai/__init__.py
reformer_fastai/_nbdev.py
reformer_fastai/all.py
reformer_fastai/attention.py
reformer_fastai/configs.py
reformer_fastai/core.py
reformer_fastai/data.py
reformer_fastai/expscript.py
reformer_fastai/layers.py
reformer_fastai/metrics.py
reformer_fastai/optimizers.py
reformer_fastai/reformer.py
reformer_fastai/tokenizers.py
reformer_fastai/tracking.py
reformer_fastai/transformer.py
reformer_fastai-0.0.2.dist-info/LICENSE
reformer_fastai-0.0.2.dist-info/METADATA
reformer_fastai-0.0.2.dist-info/WHEEL
reformer_fastai-0.0.2.dist-info/entry_points.txt
reformer_fastai-0.0.2.dist-info/top_level.txt
reformer_fastai-0.0.2.dist-info/RECORD
