Metadata-Version: 2.1
Name: reformer-fastai
Version: 0.0.2
Summary: Fastai community entry to 2020 Reproducibility Challenge
Home-page: https://github.com/arampacha/reformer_fastai/tree/master/
Author: Fastai community
Author-email: aruthart@gmail.com
License: MIT License
Keywords: fastai reformer
Platform: UNKNOWN
Classifier: Development Status :: 3 - Alpha
Classifier: Intended Audience :: Developers
Classifier: License :: OSI Approved :: MIT License
Classifier: Natural Language :: English
Classifier: Programming Language :: Python :: 3.6
Classifier: Programming Language :: Python :: 3.7
Classifier: Programming Language :: Python :: 3.8
Requires-Python: >=3.6
Requires-Dist: torch (>=1.7.0)
Requires-Dist: fastai (<2.3,>=2.2.2)
Requires-Dist: fastcore (>=1.3.19)
Requires-Dist: einops
Requires-Dist: torchvision (>=0.8)
Requires-Dist: spacy (>=2.2.4)
Requires-Dist: matplotlib
Requires-Dist: axial-positional-embedding
Requires-Dist: datasets
